{"cameraMode":{"drawMode":6,"name":"Overdraw","section":"Miscellaneous"},"sceneLighting":false,"audioPlay":false,"sceneViewState":{"m_AlwaysRefresh":false,"showFog":true,"showSkybox":false,"showFlares":true,"showImageEffects":true,"showParticleSystems":true,"showVisualEffectGraphs":true,"m_FxEnabled":true},"in2DMode":false,"pivot":{"x":-7.684112548828125,"y":53.099998474121097,"z":-645.9000244140625},"rotation":{"x":0.09297297149896622,"y":-0.8971002697944641,"z":0.3675106465816498,"w":0.22696106135845185},"size":55.99618148803711,"orthographic":false}